mula/__init__.py
mula/adpaters.py
pymula-0.0.1.dist-info/METADATA
pymula-0.0.1.dist-info/RECORD
pymula-0.0.1.dist-info/WHEEL
pymula-0.0.1.dist-info/top_level.txt
