Metadata-Version: 2.1
Name: pymula
Version: 0.0.1
Summary: Cellulant Mula Python adapter
Home-page: https://goodup.com
Author: Loek van Gent
Author-email: hallo@loekvan.gent
License: GPLv3+
Platform: UNKNOWN
Classifier: Environment :: Web Environment
Classifier: Intended Audience :: Developers
Classifier: Operating System :: OS Independent
Classifier: Programming Language :: Python
Classifier: Topic :: Internet :: WWW/HTTP
Classifier: Topic :: Internet :: WWW/HTTP :: Dynamic Content
Requires-Dist: suds
Requires-Dist: requests[security] (==2.8.1)
